alsgls/__init__.py
alsgls/als.py
alsgls/em.py
alsgls/metrics.py
alsgls/ops.py
alsgls/sim.py
alsgls-0.1.0.dist-info/METADATA
alsgls-0.1.0.dist-info/WHEEL
alsgls-0.1.0.dist-info/top_level.txt
alsgls-0.1.0.dist-info/RECORD
