Metadata-Version: 2.4
Name: alsgls
Version: 0.1.0
Summary: Lightweight low-rank+diag GLS/SUR via ALS with EM baseline
Author-email: Gaurav Sood <contact@gsood.com>
License: MIT
Project-URL: Homepage, https://github.com/finite-sample/alsgls
Classifier: Programming Language :: Python :: 3
Classifier: License :: OSI Approved :: MIT License
Classifier: Operating System :: OS Independent
Requires-Python: >=3.9
Requires-Dist: numpy>=1.21
Provides-Extra: dev
Requires-Dist: pytest>=7.0; extra == "dev"
